Eridanus/__init__.py
Eridanus/adapters/__init__.py
Eridanus/adapters/http_adapter.py
Eridanus/adapters/websocket_adapter.py
Eridanus/event/__init__.py
Eridanus/event/base.py
Eridanus/event/bus.py
Eridanus/event/eventFactory.py
Eridanus/event/events.py
Eridanus/interface/__init__.py
Eridanus/interface/http_sendMes.py
Eridanus/interface/websocket_sendMes.py
Eridanus/message/__init__.py
Eridanus/message/message_chain.py
Eridanus/message/message_components.py
Eridanus/utils/__init__.py
Eridanus/utils/cq_code_handler.py
Eridanus/utils/logger.py
eridanus_dep-0.1.5.dist-info/LICENSE
eridanus_dep-0.1.5.dist-info/METADATA
eridanus_dep-0.1.5.dist-info/WHEEL
eridanus_dep-0.1.5.dist-info/top_level.txt
eridanus_dep-0.1.5.dist-info/RECORD
