Metadata-Version: 2.1
Name: eridanus-dep
Version: 0.1.5
Summary: 轻量化的onebot v11 sdk
Home-page: https://github.com/avilliai/eridanus-dep
Author: Alpherg
Author-email: larea06@gmail.com
License-File: LICENSE
Requires-Dist: httpx
Requires-Dist: websockets
Requires-Dist: pydantic
Requires-Dist: colorlog
